{"version":2,"kind":"Article","sha256":"29febdf70721814e9726d73eac65eb8cc621e02c413680dd83282e9eaafeb23e","slug":"index","location":"/index.md","dependencies":[],"frontmatter":{"title":"DestinE Data Lake Gallery","content_includes_title":false,"exports":[{"format":"md","filename":"index.md","url":"/index-380f92a2a504ecf3d56f0bafd651e0a5.md"}]},"mdast":{"type":"root","children":[{"type":"block","children":[{"type":"paragraph","position":{"start":{"line":3,"column":1},"end":{"line":5,"column":1}},"children":[{"type":"strong","position":{"start":{"line":3,"column":1},"end":{"line":3,"column":1}},"children":[{"type":"text","value":"Welcome to the Destination Earth Data Lake Notebook Gallery!","position":{"start":{"line":3,"column":1},"end":{"line":3,"column":1}},"key":"Hhcdkjfg4B"}],"key":"v8d5pfjdA8"},{"type":"text","value":" ","position":{"start":{"line":3,"column":1},"end":{"line":3,"column":1}},"key":"eFRioPdawo"},{"type":"break","key":"GEIyh3JSSR"},{"type":"text","value":"\nExplore our collection of interactive Jupyter Notebooks, designed to help you work with the wide range of services offered by the DestinE Data Lake. Each notebook provides hands-on examples and practical guidance that you can adapt for your own projects. ","position":{"start":{"line":3,"column":1},"end":{"line":3,"column":1}},"key":"a8L3q4lFPb"},{"type":"break","key":"yxBC9C5VyJ"},{"type":"text","value":"\nUse the tag filters to quickly find notebooks relevant to your interests or workflow. Tags group notebooks by topic, data source, or functionality, making it easier to navigate the gallery and locate the examples most useful for your work.","position":{"start":{"line":3,"column":1},"end":{"line":3,"column":1}},"key":"juGR6PWXp8"}],"key":"dic74RhcHO"},{"type":"thematicBreak","position":{"start":{"line":7,"column":1},"end":{"line":7,"column":1}},"key":"LL6cODy2wg"},{"type":"heading","depth":3,"position":{"start":{"line":9,"column":1},"end":{"line":9,"column":1}},"children":[{"type":"text","value":"Filter Notebooks by Tags","position":{"start":{"line":9,"column":1},"end":{"line":9,"column":1}},"key":"GDY7H6Im6m"}],"identifier":"filter-notebooks-by-tags","label":"Filter Notebooks by Tags","html_id":"filter-notebooks-by-tags","implicit":true,"key":"E2y01RoTE6"},{"type":"paragraph","position":{"start":{"line":18,"column":1},"end":{"line":43,"column":1}},"children":[{"type":"link","url":"/tag-access-token","children":[{"type":"text","value":"Access Token","key":"tPtCwQl1U2"}],"class":"button","urlSource":"galleries_by_tag/tag-access-token.md","dataUrl":"/tag-access-token.json","internal":true,"protocol":"file","key":"z5GxtuTUIN"},{"type":"text","value":"\n","position":{"start":{"line":18,"column":1},"end":{"line":18,"column":1}},"key":"PzzCS5fVj4"},{"type":"link","url":"/tag-authentication","children":[{"type":"text","value":"Authentication","key":"CNFcU23COV"}],"class":"button","urlSource":"galleries_by_tag/tag-authentication.md","dataUrl":"/tag-authentication.json","internal":true,"protocol":"file","key":"KvA6k6hlhQ"},{"type":"text","value":"\n","position":{"start":{"line":18,"column":1},"end":{"line":18,"column":1}},"key":"zhAEnuS3ub"},{"type":"link","url":"/tag-avhrr","children":[{"type":"text","value":"AVHRR","key":"WR1Dlq2EMk"}],"class":"button","urlSource":"galleries_by_tag/tag-avhrr.md","dataUrl":"/tag-avhrr.json","internal":true,"protocol":"file","key":"XWdVl92mq0"},{"type":"text","value":"\n","position":{"start":{"line":18,"column":1},"end":{"line":18,"column":1}},"key":"M1yxHguZ9T"},{"type":"link","url":"/tag-c3s","children":[{"type":"text","value":"C3S","key":"QK70vdTfcc"}],"class":"button","urlSource":"galleries_by_tag/tag-c3s.md","dataUrl":"/tag-c3s.json","internal":true,"protocol":"file","key":"gs4hcnc5XG"},{"type":"text","value":"\n","position":{"start":{"line":18,"column":1},"end":{"line":18,"column":1}},"key":"Fj1SFbWMfD"},{"type":"link","url":"/tag-cluster","children":[{"type":"text","value":"Cluster","key":"BluQbAoNBa"}],"class":"button","urlSource":"galleries_by_tag/tag-cluster.md","dataUrl":"/tag-cluster.json","internal":true,"protocol":"file","key":"j7SZ3NVBdd"},{"type":"text","value":"\n","position":{"start":{"line":18,"column":1},"end":{"line":18,"column":1}},"key":"s4Ykq9nuWb"},{"type":"link","url":"/tag-core-api","children":[{"type":"text","value":"Core API","key":"ob8y3b0wGp"}],"class":"button","urlSource":"galleries_by_tag/tag-core-api.md","dataUrl":"/tag-core-api.json","internal":true,"protocol":"file","key":"kpa1dQWOhC"},{"type":"text","value":"\n","position":{"start":{"line":18,"column":1},"end":{"line":18,"column":1}},"key":"Tgaf8Q3hpz"},{"type":"link","url":"/tag-dask","children":[{"type":"text","value":"Dask","key":"zrUwXU9uHD"}],"class":"button","urlSource":"galleries_by_tag/tag-dask.md","dataUrl":"/tag-dask.json","internal":true,"protocol":"file","key":"C9Q07JLWIr"},{"type":"text","value":"\n","position":{"start":{"line":18,"column":1},"end":{"line":18,"column":1}},"key":"hytEGW0wzR"},{"type":"link","url":"/tag-digital-twin","children":[{"type":"text","value":"Digital Twin","key":"uEhOMF7NUh"}],"class":"button","urlSource":"galleries_by_tag/tag-digital-twin.md","dataUrl":"/tag-digital-twin.json","internal":true,"protocol":"file","key":"OO7KNmcGgD"},{"type":"text","value":"\n","position":{"start":{"line":18,"column":1},"end":{"line":18,"column":1}},"key":"le9mreFRLT"},{"type":"link","url":"/tag-earthkit","children":[{"type":"text","value":"earthkit","key":"WZNJqq8WuD"}],"class":"button","urlSource":"galleries_by_tag/tag-earthkit.md","dataUrl":"/tag-earthkit.json","internal":true,"protocol":"file","key":"Jo1n6wSTvl"},{"type":"text","value":"\n","position":{"start":{"line":18,"column":1},"end":{"line":18,"column":1}},"key":"t2GhueO4Y2"},{"type":"link","url":"/tag-ecmwf","children":[{"type":"text","value":"ECMWF","key":"nQ85XpJ5NX"}],"class":"button","urlSource":"galleries_by_tag/tag-ecmwf.md","dataUrl":"/tag-ecmwf.json","internal":true,"protocol":"file","key":"RaVe8FVAH5"},{"type":"text","value":"\n","position":{"start":{"line":18,"column":1},"end":{"line":18,"column":1}},"key":"DrfVZFE5NQ"},{"type":"link","url":"/tag-eodag","children":[{"type":"text","value":"EODAG","key":"M5Uz3HBKOn"}],"class":"button","urlSource":"galleries_by_tag/tag-eodag.md","dataUrl":"/tag-eodag.json","internal":true,"protocol":"file","key":"BjiGTGRYGX"},{"type":"text","value":"\n","position":{"start":{"line":18,"column":1},"end":{"line":18,"column":1}},"key":"H2rTCxhNZ8"},{"type":"link","url":"/tag-gfm","children":[{"type":"text","value":"GFM","key":"THdROaTmKt"}],"class":"button","urlSource":"galleries_by_tag/tag-gfm.md","dataUrl":"/tag-gfm.json","internal":true,"protocol":"file","key":"pnX9rwjGXa"},{"type":"text","value":"\n","position":{"start":{"line":18,"column":1},"end":{"line":18,"column":1}},"key":"B81EffDeXZ"},{"type":"link","url":"/tag-hda","children":[{"type":"text","value":"HDA","key":"b9BjU3xvXx"}],"class":"button","urlSource":"galleries_by_tag/tag-hda.md","dataUrl":"/tag-hda.json","internal":true,"protocol":"file","key":"PR2TG942fy"},{"type":"text","value":"\n","position":{"start":{"line":18,"column":1},"end":{"line":18,"column":1}},"key":"Vh7fPLbHpi"},{"type":"link","url":"/tag-hook","children":[{"type":"text","value":"Hook","key":"YNq5Akx9GR"}],"class":"button","urlSource":"galleries_by_tag/tag-hook.md","dataUrl":"/tag-hook.json","internal":true,"protocol":"file","key":"oW63d3XWqw"},{"type":"text","value":"\n","position":{"start":{"line":18,"column":1},"end":{"line":18,"column":1}},"key":"MkF1f4Z1bq"},{"type":"link","url":"/tag-http-requests","children":[{"type":"text","value":"HTTP requests","key":"YgY0ofMnYT"}],"class":"button","urlSource":"galleries_by_tag/tag-http-requests.md","dataUrl":"/tag-http-requests.json","internal":true,"protocol":"file","key":"WTOJrjP1OF"},{"type":"text","value":"\n","position":{"start":{"line":18,"column":1},"end":{"line":18,"column":1}},"key":"w2nLACQdze"},{"type":"link","url":"/tag-metop","children":[{"type":"text","value":"Metop","key":"MLPu4qR9q6"}],"class":"button","urlSource":"galleries_by_tag/tag-metop.md","dataUrl":"/tag-metop.json","internal":true,"protocol":"file","key":"OTwKsEzzJK"},{"type":"text","value":"\n","position":{"start":{"line":18,"column":1},"end":{"line":18,"column":1}},"key":"JNTEQ32lyU"},{"type":"link","url":"/tag-olci","children":[{"type":"text","value":"OLCI","key":"REv21YuDNo"}],"class":"button","urlSource":"galleries_by_tag/tag-olci.md","dataUrl":"/tag-olci.json","internal":true,"protocol":"file","key":"cDnDo5naFX"},{"type":"text","value":"\n","position":{"start":{"line":18,"column":1},"end":{"line":18,"column":1}},"key":"dC3PqCWynR"},{"type":"link","url":"/tag-pyaviso","children":[{"type":"text","value":"pyaviso","key":"b5OfzHriJ9"}],"class":"button","urlSource":"galleries_by_tag/tag-pyaviso.md","dataUrl":"/tag-pyaviso.json","internal":true,"protocol":"file","key":"OaJ6FhalTi"},{"type":"text","value":"\n","position":{"start":{"line":18,"column":1},"end":{"line":18,"column":1}},"key":"IDXDZNYPYq"},{"type":"link","url":"/tag-satpy","children":[{"type":"text","value":"satpy","key":"DYdSi9YOCA"}],"class":"button","urlSource":"galleries_by_tag/tag-satpy.md","dataUrl":"/tag-satpy.json","internal":true,"protocol":"file","key":"yfulqiOyVi"},{"type":"text","value":"\n","position":{"start":{"line":18,"column":1},"end":{"line":18,"column":1}},"key":"gs7IqhH78y"},{"type":"link","url":"/tag-sentinel-3","children":[{"type":"text","value":"Sentinel-3","key":"E1KKHJG7Vb"}],"class":"button","urlSource":"galleries_by_tag/tag-sentinel-3.md","dataUrl":"/tag-sentinel-3.json","internal":true,"protocol":"file","key":"nP0jAQJiFe"},{"type":"text","value":"\n","position":{"start":{"line":18,"column":1},"end":{"line":18,"column":1}},"key":"kcTLZmApuz"},{"type":"link","url":"/tag-seviri","children":[{"type":"text","value":"SEVIRI","key":"V8KF4fVIQ4"}],"class":"button","urlSource":"galleries_by_tag/tag-seviri.md","dataUrl":"/tag-seviri.json","internal":true,"protocol":"file","key":"Mc7q9DRBOE"},{"type":"text","value":"\n","position":{"start":{"line":18,"column":1},"end":{"line":18,"column":1}},"key":"jgZYfQsSWU"},{"type":"link","url":"/tag-stac","children":[{"type":"text","value":"STAC","key":"leLMrEEjov"}],"class":"button","urlSource":"galleries_by_tag/tag-stac.md","dataUrl":"/tag-stac.json","internal":true,"protocol":"file","key":"Z21KmYTo2v"},{"type":"text","value":"\n","position":{"start":{"line":18,"column":1},"end":{"line":18,"column":1}},"key":"e82dPhjZ0C"},{"type":"link","url":"/tag-stack","children":[{"type":"text","value":"STACK","key":"XRpvuHDrgB"}],"class":"button","urlSource":"galleries_by_tag/tag-stack.md","dataUrl":"/tag-stack.json","internal":true,"protocol":"file","key":"Ejfa3DdWBb"},{"type":"text","value":"\n","position":{"start":{"line":18,"column":1},"end":{"line":18,"column":1}},"key":"K92culSAGl"},{"type":"link","url":"/tag-storage","children":[{"type":"text","value":"Storage","key":"TaVHzAZ7B3"}],"class":"button","urlSource":"galleries_by_tag/tag-storage.md","dataUrl":"/tag-storage.json","internal":true,"protocol":"file","key":"Mjgpa6zAfW"},{"type":"text","value":"\n","position":{"start":{"line":18,"column":1},"end":{"line":18,"column":1}},"key":"g4COKNKNrQ"},{"type":"link","url":"/tag-token","children":[{"type":"text","value":"Token","key":"LiLhyriIc4"}],"class":"button","urlSource":"galleries_by_tag/tag-token.md","dataUrl":"/tag-token.json","internal":true,"protocol":"file","key":"RLgLKGeeXq"},{"type":"text","value":"\n","position":{"start":{"line":18,"column":1},"end":{"line":18,"column":1}},"key":"aXUDLoOeul"},{"type":"link","url":"/tag-workflow","children":[{"type":"text","value":"Workflow","key":"DThzjL1GQN"}],"class":"button","urlSource":"galleries_by_tag/tag-workflow.md","dataUrl":"/tag-workflow.json","internal":true,"protocol":"file","key":"VhPLU4axxH"}],"key":"VJV02MkWkI"},{"type":"thematicBreak","position":{"start":{"line":45,"column":1},"end":{"line":45,"column":1}},"key":"txA80AtCrb"},{"type":"heading","depth":3,"position":{"start":{"line":47,"column":1},"end":{"line":47,"column":1}},"children":[{"type":"text","value":"Services Overview","position":{"start":{"line":47,"column":1},"end":{"line":47,"column":1}},"key":"ewdlZVK4Li"}],"identifier":"services-overview","label":"Services Overview","html_id":"services-overview","implicit":true,"key":"P3593St0wZ"},{"type":"paragraph","position":{"start":{"line":49,"column":1},"end":{"line":49,"column":1}},"children":[{"type":"text","value":"The DestinE Data Lake provides three main services to help you discover, process, and manage data:","position":{"start":{"line":49,"column":1},"end":{"line":49,"column":1}},"key":"P8FpT3YFDa"}],"key":"W8Lj5MsyIS"},{"type":"list","ordered":false,"spread":false,"position":{"start":{"line":51,"column":1},"end":{"line":54,"column":1}},"children":[{"type":"listItem","spread":true,"position":{"start":{"line":51,"column":1},"end":{"line":51,"column":1}},"children":[{"type":"paragraph","children":[{"type":"strong","position":{"start":{"line":51,"column":1},"end":{"line":51,"column":1}},"children":[{"type":"link","url":"https://hda.data.destination-earth.eu/stac","position":{"start":{"line":51,"column":1},"end":{"line":51,"column":1}},"children":[{"type":"text","value":"Harmonised Data Access (HDA)","position":{"start":{"line":51,"column":1},"end":{"line":51,"column":1}},"key":"E3eTnElDBM"}],"urlSource":"https://hda.data.destination-earth.eu/stac","key":"XyzJfHnpxk"}],"key":"VfnTuYrIWb"},{"type":"text","value":" – Browse Jupyter Notebook examples and Python tools for the DEDL Harmonised Data Access.","position":{"start":{"line":51,"column":1},"end":{"line":51,"column":1}},"key":"do8x4e6T9l"}],"key":"ZDYggzg4wV"}],"key":"ZL2d9X0TVF"},{"type":"listItem","spread":true,"position":{"start":{"line":52,"column":1},"end":{"line":52,"column":1}},"children":[{"type":"paragraph","children":[{"type":"strong","position":{"start":{"line":52,"column":1},"end":{"line":52,"column":1}},"children":[{"type":"link","url":"https://s3.central.data.destination-earth.eu/swift/v1/dedl_datacube","position":{"start":{"line":52,"column":1},"end":{"line":52,"column":1}},"children":[{"type":"text","value":"STACK service","position":{"start":{"line":52,"column":1},"end":{"line":52,"column":1}},"key":"Z1BO6wn5mK"}],"urlSource":"https://s3.central.data.destination-earth.eu/swift/v1/dedl_datacube","key":"prPmB2mzKA"}],"key":"y6SyDBJv6D"},{"type":"text","value":" – Leverage Dask for scalable, near-data processing of large datasets.","position":{"start":{"line":52,"column":1},"end":{"line":52,"column":1}},"key":"geK2KL2YrM"}],"key":"XfEOO38KLV"}],"key":"TO6u9RnAvy"},{"type":"listItem","spread":true,"position":{"start":{"line":53,"column":1},"end":{"line":54,"column":1}},"children":[{"type":"paragraph","children":[{"type":"strong","position":{"start":{"line":53,"column":1},"end":{"line":53,"column":1}},"children":[{"type":"link","url":"https://odp.data.destination-earth.eu/odata/v1/","position":{"start":{"line":53,"column":1},"end":{"line":53,"column":1}},"children":[{"type":"text","value":"HOOK service","position":{"start":{"line":53,"column":1},"end":{"line":53,"column":1}},"key":"vlqM2oDt9f"}],"urlSource":"https://odp.data.destination-earth.eu/odata/v1/","key":"Rxmt1aecYG"}],"key":"vszKGpGjmR"},{"type":"text","value":" – Create, manage, and automate workflows using the HOOK orchestration service.","position":{"start":{"line":53,"column":1},"end":{"line":53,"column":1}},"key":"scUi1uvRaG"}],"key":"I1T6szOSJZ"}],"key":"i3ZyaLMCBd"}],"key":"wd6mdvAWmX"},{"type":"thematicBreak","position":{"start":{"line":55,"column":1},"end":{"line":55,"column":1}},"key":"cndYKwmScg"},{"type":"heading","depth":3,"position":{"start":{"line":57,"column":1},"end":{"line":57,"column":1}},"children":[{"type":"text","value":"Using Notebooks on the DestinE Platform","position":{"start":{"line":57,"column":1},"end":{"line":57,"column":1}},"key":"cVfHg6vHMX"}],"identifier":"using-notebooks-on-the-destine-platform","label":"Using Notebooks on the DestinE Platform","html_id":"using-notebooks-on-the-destine-platform","implicit":true,"key":"Nb9aiWg7nt"},{"type":"paragraph","position":{"start":{"line":59,"column":1},"end":{"line":59,"column":1}},"children":[{"type":"text","value":"If you are working in the DestinE JupyterLab environment, set up your environment as follows:","position":{"start":{"line":59,"column":1},"end":{"line":59,"column":1}},"key":"qGll27WhqD"}],"key":"QoHsIuYi6u"},{"type":"code","lang":"bash","value":"# 1. Create a virtual environment\npython -m venv /home/jovyan/my_env\n\n# 2. Activate the environment\nsource /home/jovyan/my_env/bin/activate\n\n# 3. Install required dependencies\npip install -r /home/jovyan/datalake-lab/requirements.txt\n\n# 4. Register the environment as a Jupyter kernel\npython -m ipykernel install --name my_env --user","position":{"start":{"line":61,"column":1},"end":{"line":73,"column":1}},"key":"jZIj9R977T"},{"type":"paragraph","position":{"start":{"line":75,"column":1},"end":{"line":75,"column":1}},"children":[{"type":"text","value":"After installation, choose ","position":{"start":{"line":75,"column":1},"end":{"line":75,"column":1}},"key":"hdN4ToTs1m"},{"type":"inlineCode","value":"my_env","position":{"start":{"line":75,"column":1},"end":{"line":75,"column":1}},"key":"Gp0LUzao36"},{"type":"text","value":" from the Jupyter kernel menu to start running notebooks.","position":{"start":{"line":75,"column":1},"end":{"line":75,"column":1}},"key":"q4LBJEguB4"}],"key":"UpygLpjcHj"},{"type":"thematicBreak","position":{"start":{"line":77,"column":1},"end":{"line":77,"column":1}},"key":"SXpb3r6goZ"},{"type":"heading","depth":2,"position":{"start":{"line":79,"column":1},"end":{"line":79,"column":1}},"children":[{"type":"text","value":"Want to Contribute?","position":{"start":{"line":79,"column":1},"end":{"line":79,"column":1}},"key":"pW1BRzeiyC"}],"identifier":"want-to-contribute","label":"Want to Contribute?","html_id":"want-to-contribute","implicit":true,"key":"nreL8C5FCy"},{"type":"paragraph","position":{"start":{"line":81,"column":1},"end":{"line":81,"column":1}},"children":[{"type":"text","value":"Have a useful notebook to share? Check out our ","position":{"start":{"line":81,"column":1},"end":{"line":81,"column":1}},"key":"yCXkQkzHqq"},{"type":"link","url":"/contribute","position":{"start":{"line":81,"column":1},"end":{"line":81,"column":1}},"children":[{"type":"text","value":"Contributing Guide","position":{"start":{"line":81,"column":1},"end":{"line":81,"column":1}},"key":"BwXmovvnct"}],"urlSource":"contribute.md","dataUrl":"/contribute.json","internal":true,"protocol":"file","key":"I9AgHsTJ70"},{"type":"text","value":" to learn how to add it to the gallery.","position":{"start":{"line":81,"column":1},"end":{"line":81,"column":1}},"key":"eETysuYmCa"}],"key":"eA8JxKaNsi"},{"type":"thematicBreak","position":{"start":{"line":83,"column":1},"end":{"line":83,"column":1}},"key":"EpeLZvOjVj"},{"type":"heading","depth":2,"position":{"start":{"line":85,"column":1},"end":{"line":85,"column":1}},"children":[{"type":"text","value":"Learn More","position":{"start":{"line":85,"column":1},"end":{"line":85,"column":1}},"key":"KIn7JSvyzE"}],"identifier":"learn-more","label":"Learn More","html_id":"learn-more","implicit":true,"key":"w6QtmxHjfB"},{"type":"list","ordered":false,"spread":false,"position":{"start":{"line":87,"column":1},"end":{"line":89,"column":1}},"children":[{"type":"listItem","spread":true,"position":{"start":{"line":87,"column":1},"end":{"line":87,"column":1}},"children":[{"type":"paragraph","children":[{"type":"link","url":"https://destine-data-lake-docs.data.destination-earth.eu/en/latest/index.html","position":{"start":{"line":87,"column":1},"end":{"line":87,"column":1}},"children":[{"type":"text","value":"DestinE Documentation","position":{"start":{"line":87,"column":1},"end":{"line":87,"column":1}},"key":"c3TPuWANBW"}],"urlSource":"https://destine-data-lake-docs.data.destination-earth.eu/en/latest/index.html","key":"UzQDHiWHqe"},{"type":"text","value":" – Full platform and service documentation.","position":{"start":{"line":87,"column":1},"end":{"line":87,"column":1}},"key":"QQdYzwCWFH"}],"key":"faFH5j9j7D"}],"key":"Z2b8VZKDwO"},{"type":"listItem","spread":true,"position":{"start":{"line":88,"column":1},"end":{"line":88,"column":1}},"children":[{"type":"paragraph","children":[{"type":"link","url":"https://hda.data.destination-earth.eu/ui/catalog","position":{"start":{"line":88,"column":1},"end":{"line":88,"column":1}},"children":[{"type":"text","value":"DestinE Data Portfolio","position":{"start":{"line":88,"column":1},"end":{"line":88,"column":1}},"key":"NXBDkLONWy"}],"urlSource":"https://hda.data.destination-earth.eu/ui/catalog","key":"sxoqWlyJRD"},{"type":"text","value":" – Browse available datasets.","position":{"start":{"line":88,"column":1},"end":{"line":88,"column":1}},"key":"CSmEX5Clyf"}],"key":"zAOJ0Ym2el"}],"key":"d89wx0ZnV9"},{"type":"listItem","spread":true,"position":{"start":{"line":89,"column":1},"end":{"line":89,"column":1}},"children":[{"type":"paragraph","children":[{"type":"link","url":"https://hda.data.destination-earth.eu/docs/","position":{"start":{"line":89,"column":1},"end":{"line":89,"column":1}},"children":[{"type":"text","value":"API Documentation (Swagger)","position":{"start":{"line":89,"column":1},"end":{"line":89,"column":1}},"key":"r8uSECPWtZ"}],"urlSource":"https://hda.data.destination-earth.eu/docs/","key":"kHhutjW2UW"},{"type":"text","value":" – Explore the API endpoints and capabilities.","position":{"start":{"line":89,"column":1},"end":{"line":89,"column":1}},"key":"SxQF2bQYo6"}],"key":"LMVFVDArHJ"}],"key":"ZLN8tDZ1La"}],"key":"hxsNEI08tN"}],"key":"ec0mL8ZC3q"}],"key":"fkID220R35"},"references":{"cite":{"order":[],"data":{}}}}