{"version":2,"kind":"Article","sha256":"8a2cac05c1a7e8586ccce61d41dceaa2c38cdd841aaa09de8421325c710559b2","slug":"tag-storage","location":"/galleries_by_tag/tag-storage.md","dependencies":[],"frontmatter":{"title":"Notebooks Storage","content_includes_title":false,"thumbnail":"/EUMETSAT-icon-5622ee4581d60335c28e91839e666bbf.png","exports":[{"format":"md","filename":"tag-storage.md","url":"/tag-storage-1c000ee605e387bee1bb2a26652100fc.md"}]},"mdast":{"type":"root","children":[{"type":"block","children":[{"type":"heading","depth":2,"position":{"start":{"line":3,"column":1},"end":{"line":3,"column":1}},"children":[{"type":"text","value":"Filter Notebooks by Tags","position":{"start":{"line":3,"column":1},"end":{"line":3,"column":1}},"key":"bW52dk9PmZ"}],"identifier":"filter-notebooks-by-tags","label":"Filter Notebooks by Tags","html_id":"filter-notebooks-by-tags","implicit":true,"key":"X2wxfpVbij"},{"type":"paragraph","position":{"start":{"line":5,"column":1},"end":{"line":30,"column":1}},"children":[{"type":"link","url":"/tag-access-token","children":[{"type":"text","value":"Access Token","key":"Rx46WXPkjh"}],"class":"button","urlSource":"/galleries_by_tag/tag-access-token.md","dataUrl":"/tag-access-token.json","internal":true,"protocol":"file","key":"kwtPldAbiL"},{"type":"text","value":"\n","position":{"start":{"line":5,"column":1},"end":{"line":5,"column":1}},"key":"DApVlmgc63"},{"type":"link","url":"/tag-authentication","children":[{"type":"text","value":"Authentication","key":"lHehVRKg5l"}],"class":"button","urlSource":"/galleries_by_tag/tag-authentication.md","dataUrl":"/tag-authentication.json","internal":true,"protocol":"file","key":"O2Wr37S14U"},{"type":"text","value":"\n","position":{"start":{"line":5,"column":1},"end":{"line":5,"column":1}},"key":"pweIWwgmTp"},{"type":"link","url":"/tag-avhrr","children":[{"type":"text","value":"AVHRR","key":"TcAyCyQD2i"}],"class":"button","urlSource":"/galleries_by_tag/tag-avhrr.md","dataUrl":"/tag-avhrr.json","internal":true,"protocol":"file","key":"tAnaT2m1wr"},{"type":"text","value":"\n","position":{"start":{"line":5,"column":1},"end":{"line":5,"column":1}},"key":"mY8JbEJiy9"},{"type":"link","url":"/tag-c3s","children":[{"type":"text","value":"C3S","key":"BdQdnlALzu"}],"class":"button","urlSource":"/galleries_by_tag/tag-c3s.md","dataUrl":"/tag-c3s.json","internal":true,"protocol":"file","key":"sVJPyC3bUS"},{"type":"text","value":"\n","position":{"start":{"line":5,"column":1},"end":{"line":5,"column":1}},"key":"RnZHdRp7Vv"},{"type":"link","url":"/tag-cluster","children":[{"type":"text","value":"Cluster","key":"LfX9AJdB05"}],"class":"button","urlSource":"/galleries_by_tag/tag-cluster.md","dataUrl":"/tag-cluster.json","internal":true,"protocol":"file","key":"jn8aVYQT5l"},{"type":"text","value":"\n","position":{"start":{"line":5,"column":1},"end":{"line":5,"column":1}},"key":"RkSv27Pkuo"},{"type":"link","url":"/tag-core-api","children":[{"type":"text","value":"Core API","key":"ipMwkka4CE"}],"class":"button","urlSource":"/galleries_by_tag/tag-core-api.md","dataUrl":"/tag-core-api.json","internal":true,"protocol":"file","key":"XYRLEanj21"},{"type":"text","value":"\n","position":{"start":{"line":5,"column":1},"end":{"line":5,"column":1}},"key":"UvMoqGJBxW"},{"type":"link","url":"/tag-dask","children":[{"type":"text","value":"Dask","key":"mrKV9ke0En"}],"class":"button","urlSource":"/galleries_by_tag/tag-dask.md","dataUrl":"/tag-dask.json","internal":true,"protocol":"file","key":"icCUWr59pQ"},{"type":"text","value":"\n","position":{"start":{"line":5,"column":1},"end":{"line":5,"column":1}},"key":"SwqCvU8Km5"},{"type":"link","url":"/tag-digital-twin","children":[{"type":"text","value":"Digital Twin","key":"nunSAESSga"}],"class":"button","urlSource":"/galleries_by_tag/tag-digital-twin.md","dataUrl":"/tag-digital-twin.json","internal":true,"protocol":"file","key":"r8rffpb7GL"},{"type":"text","value":"\n","position":{"start":{"line":5,"column":1},"end":{"line":5,"column":1}},"key":"vdcNxY3hdB"},{"type":"link","url":"/tag-earthkit","children":[{"type":"text","value":"earthkit","key":"NXEd3tyA7v"}],"class":"button","urlSource":"/galleries_by_tag/tag-earthkit.md","dataUrl":"/tag-earthkit.json","internal":true,"protocol":"file","key":"RZ7Xld6bN6"},{"type":"text","value":"\n","position":{"start":{"line":5,"column":1},"end":{"line":5,"column":1}},"key":"dfv60InwwC"},{"type":"link","url":"/tag-ecmwf","children":[{"type":"text","value":"ECMWF","key":"enh6HWJorv"}],"class":"button","urlSource":"/galleries_by_tag/tag-ecmwf.md","dataUrl":"/tag-ecmwf.json","internal":true,"protocol":"file","key":"LYBp8ZdmEe"},{"type":"text","value":"\n","position":{"start":{"line":5,"column":1},"end":{"line":5,"column":1}},"key":"cj70OwPerd"},{"type":"link","url":"/tag-eodag","children":[{"type":"text","value":"EODAG","key":"jead3TPOBU"}],"class":"button","urlSource":"/galleries_by_tag/tag-eodag.md","dataUrl":"/tag-eodag.json","internal":true,"protocol":"file","key":"Oew713CEjn"},{"type":"text","value":"\n","position":{"start":{"line":5,"column":1},"end":{"line":5,"column":1}},"key":"jhvLhUKbPY"},{"type":"link","url":"/tag-gfm","children":[{"type":"text","value":"GFM","key":"kvogRP2Qx4"}],"class":"button","urlSource":"/galleries_by_tag/tag-gfm.md","dataUrl":"/tag-gfm.json","internal":true,"protocol":"file","key":"lds78GFzha"},{"type":"text","value":"\n","position":{"start":{"line":5,"column":1},"end":{"line":5,"column":1}},"key":"TrMkZQYeYA"},{"type":"link","url":"/tag-hda","children":[{"type":"text","value":"HDA","key":"HNXUf3WYEG"}],"class":"button","urlSource":"/galleries_by_tag/tag-hda.md","dataUrl":"/tag-hda.json","internal":true,"protocol":"file","key":"LmjSaKWFHG"},{"type":"text","value":"\n","position":{"start":{"line":5,"column":1},"end":{"line":5,"column":1}},"key":"ZEQSZs85De"},{"type":"link","url":"/tag-hook","children":[{"type":"text","value":"Hook","key":"mcOOXJ1Wam"}],"class":"button","urlSource":"/galleries_by_tag/tag-hook.md","dataUrl":"/tag-hook.json","internal":true,"protocol":"file","key":"bdOI6CzvLB"},{"type":"text","value":"\n","position":{"start":{"line":5,"column":1},"end":{"line":5,"column":1}},"key":"mhyAiKdkKQ"},{"type":"link","url":"/tag-http-requests","children":[{"type":"text","value":"HTTP requests","key":"JWgWr52Iol"}],"class":"button","urlSource":"/galleries_by_tag/tag-http-requests.md","dataUrl":"/tag-http-requests.json","internal":true,"protocol":"file","key":"r4UhmhJhXM"},{"type":"text","value":"\n","position":{"start":{"line":5,"column":1},"end":{"line":5,"column":1}},"key":"lxZNZNC451"},{"type":"link","url":"/tag-metop","children":[{"type":"text","value":"Metop","key":"UAnCeovAfz"}],"class":"button","urlSource":"/galleries_by_tag/tag-metop.md","dataUrl":"/tag-metop.json","internal":true,"protocol":"file","key":"KSqIGdSAFj"},{"type":"text","value":"\n","position":{"start":{"line":5,"column":1},"end":{"line":5,"column":1}},"key":"Az8fXeylnV"},{"type":"link","url":"/tag-olci","children":[{"type":"text","value":"OLCI","key":"Tmd8TByTqm"}],"class":"button","urlSource":"/galleries_by_tag/tag-olci.md","dataUrl":"/tag-olci.json","internal":true,"protocol":"file","key":"tpmJSm6nmw"},{"type":"text","value":"\n","position":{"start":{"line":5,"column":1},"end":{"line":5,"column":1}},"key":"aJYJ610Hlc"},{"type":"link","url":"/tag-pyaviso","children":[{"type":"text","value":"pyaviso","key":"D58MzK1GgZ"}],"class":"button","urlSource":"/galleries_by_tag/tag-pyaviso.md","dataUrl":"/tag-pyaviso.json","internal":true,"protocol":"file","key":"ipRC4ubrge"},{"type":"text","value":"\n","position":{"start":{"line":5,"column":1},"end":{"line":5,"column":1}},"key":"Pi02WMd8qL"},{"type":"link","url":"/tag-satpy","children":[{"type":"text","value":"satpy","key":"CeZF9jD5zO"}],"class":"button","urlSource":"/galleries_by_tag/tag-satpy.md","dataUrl":"/tag-satpy.json","internal":true,"protocol":"file","key":"pwlvN4h01S"},{"type":"text","value":"\n","position":{"start":{"line":5,"column":1},"end":{"line":5,"column":1}},"key":"wqYheZjNlC"},{"type":"link","url":"/tag-sentinel-3","children":[{"type":"text","value":"Sentinel-3","key":"q4ISbzJp4Y"}],"class":"button","urlSource":"/galleries_by_tag/tag-sentinel-3.md","dataUrl":"/tag-sentinel-3.json","internal":true,"protocol":"file","key":"x4hLJjjxXS"},{"type":"text","value":"\n","position":{"start":{"line":5,"column":1},"end":{"line":5,"column":1}},"key":"Q2fnShiPVV"},{"type":"link","url":"/tag-seviri","children":[{"type":"text","value":"SEVIRI","key":"HN5jf2aweD"}],"class":"button","urlSource":"/galleries_by_tag/tag-seviri.md","dataUrl":"/tag-seviri.json","internal":true,"protocol":"file","key":"WZDb1qCiVk"},{"type":"text","value":"\n","position":{"start":{"line":5,"column":1},"end":{"line":5,"column":1}},"key":"UOuqIP2Vgq"},{"type":"link","url":"/tag-stac","children":[{"type":"text","value":"STAC","key":"NSF08shGtR"}],"class":"button","urlSource":"/galleries_by_tag/tag-stac.md","dataUrl":"/tag-stac.json","internal":true,"protocol":"file","key":"QAL8PUBmff"},{"type":"text","value":"\n","position":{"start":{"line":5,"column":1},"end":{"line":5,"column":1}},"key":"fi8CG4gLGq"},{"type":"link","url":"/tag-stack","children":[{"type":"text","value":"STACK","key":"gKP4Aeab7j"}],"class":"button","urlSource":"/galleries_by_tag/tag-stack.md","dataUrl":"/tag-stack.json","internal":true,"protocol":"file","key":"rygR1wzegM"},{"type":"text","value":"\n","position":{"start":{"line":5,"column":1},"end":{"line":5,"column":1}},"key":"xWnHzYM88B"},{"type":"link","url":"/tag-storage","children":[{"type":"text","value":"Storage","key":"zymJGoHQoV"}],"class":"button","urlSource":"/galleries_by_tag/tag-storage.md","dataUrl":"/tag-storage.json","internal":true,"protocol":"file","key":"Sqxxqgati6"},{"type":"text","value":"\n","position":{"start":{"line":5,"column":1},"end":{"line":5,"column":1}},"key":"z9fZuPhv80"},{"type":"link","url":"/tag-token","children":[{"type":"text","value":"Token","key":"Qc87YVRkLo"}],"class":"button","urlSource":"/galleries_by_tag/tag-token.md","dataUrl":"/tag-token.json","internal":true,"protocol":"file","key":"nhEo2xdUWK"},{"type":"text","value":"\n","position":{"start":{"line":5,"column":1},"end":{"line":5,"column":1}},"key":"Z5dVUJtdPR"},{"type":"link","url":"/tag-workflow","children":[{"type":"text","value":"Workflow","key":"x7sCXBTdB0"}],"class":"button","urlSource":"/galleries_by_tag/tag-workflow.md","dataUrl":"/tag-workflow.json","internal":true,"protocol":"file","key":"xOFvRBE30f"}],"key":"EPmFIB6uAR"},{"type":"div","style":{"display":"flex","flexDirection":"column","gap":"20px","maxWidth":"800px"},"children":[{"type":"div","class":"notebook-card","style":{"display":"flex","alignItems":"flex-start","border":"1px solid #cddff1","borderRadius":"6px","padding":"14px 20px","backgroundColor":"#f9fbfe","boxShadow":"1px 1px 4px #dfeaf5"},"children":[{"type":"div","style":{"width":"100px","height":"100px","flexShrink":"0","display":"flex","alignItems":"center","justifyContent":"center","backgroundColor":"#fff","border":"1px solid #e0eaf5","borderRadius":"6px","overflow":"hidden","marginRight":"32px"},"children":[{"type":"image","style":{"maxWidth":"100%","maxHeight":"100%","objectFit":"contain"},"url":"/EUMETSAT-icon-5622ee4581d60335c28e91839e666bbf.png","alt":"Notebook Thumbnail","key":"MDANCL8ZE4","urlSource":"../img/EUMETSAT-icon.png"}],"key":"scuoFoYukv"},{"type":"div","style":{"flex":"1"},"children":[{"type":"strong","children":[{"type":"text","value":"Hook Tutorial - Data Harvest","key":"GWlZwLLAjC"}],"key":"gMblBDbIqo"},{"type":"break","key":"kVMcq1NoDE"},{"type":"text","value":" This notebook demonstrates how to use the Hook service.","key":"sWeOwff5r6"},{"type":"div","style":{"margin":"6px 0"},"children":[{"type":"span","class":"tag","children":[{"type":"text","value":"Hook","key":"Pz4xIvTJkE"}],"key":"HCZgRipOn8"},{"type":"span","class":"tag","children":[{"type":"text","value":"Authentication","key":"pxfjiNkYWS"}],"key":"pLXcux76wv"},{"type":"span","class":"tag","children":[{"type":"text","value":"Workflow","key":"X2XbNT75Zf"}],"key":"L5fwh1EQE6"},{"type":"span","class":"tag","children":[{"type":"text","value":"Storage","key":"i6Idy3gjXn"}],"key":"PGioL3y26D"}],"key":"l2qUShh8Ty"},{"type":"link","style":{"textDecoration":"none","color":"#1d70b8","fontWeight":"bold"},"url":"/tutorial","children":[{"type":"text","value":"View Notebook","key":"zYfdUYuVwz"}],"urlSource":"../production/HOOK/Tutorial.ipynb","dataUrl":"/tutorial.json","internal":true,"protocol":"file","key":"XGVTIJSccu"}],"key":"TW1rDfIvXM"}],"key":"M66ifu5Gro"}],"key":"NjE4Njj66j"}],"key":"rA7taAw5JM"}],"key":"mSTkMWVWDB"},"references":{"cite":{"order":[],"data":{}}}}